[
  {
    "first_name": "Sal",
    "last_name": "Bologna",
    "email": "sal@gmail.com",
    "password": "password12345",
    "gender": "Male",
    "fitness_level": "Intermediate",
    "city": "Orlando",
    "state": "Florida",
    "age": "32",
    "availability": "Morning"
  },
  {
    "first_name": "Thad",
    "last_name": "Jarvis",
    "email": "radthad@hotmail.com",
    "password": "password123",
    "gender": "Male",
    "fitness_level": "Beginner",
    "city": "Longwood",
    "state": "Florida",
    "age": "22",
    "availability": "Afternoon"
  },
  {
    "first_name": "Tammy",
    "last_name": "Smith",
    "email": "tammy@hotmail.com",
    "password": "password1234",
    "gender": "Female",
    "fitness_level": "Beginner",
    "city": "Altamonte",
    "state": "Florida",
    "age": "40",
    "availability": "Evening"
  },
  {
    "first_name": "Erin",
    "last_name": "Aarons",
    "email": "erinaarons@gmail.com",
    "password": "abcd1234",
    "gender": "Female",
    "fitness_level": "Intermediate",
    "city": "Casselberry",
    "state": "Florida",
    "age": "30",
    "availability": "Morning"
  },
  {
    "first_name": "Don",
    "last_name": "Fry",
    "email": "donthedon@aol.com",
    "password": "password1123",
    "gender": "Male",
    "fitness_level": "Beginner",
    "city": "Maitland",
    "state": "Florida",
    "age": "45",
    "availability": "Afternoon"
  },
  {
    "first_name": "Debra",
    "last_name": "Downing",
    "email": "debbiedowner@protonmail.com",
    "password": "password1234",
    "gender": "Female",
    "fitness_level": "Advanced",
    "city": "Wekiwa",
    "state": "Florida",
    "age": "42",
    "availability": "Evening"
  },
  {
    "first_name": "Greg",
    "last_name": "Silverstein",
    "email": "greggg@yahoo.com",
    "password": "password22424",
    "gender": "Male",
    "fitness_level": "Advanced",
    "city": "Lake Mary",
    "state": "Florida",
    "age": "25",
    "availability": "Morning"
  },
  {
    "first_name": "Lacey",
    "last_name": "Brown",
    "email": "lacey@aol.com",
    "password": "password553",
    "gender": "Female",
    "fitness_level": "Beginner",
    "city": "Orlando",
    "state": "Florida",
    "age": "27",
    "availability": "Afternoon"
  },
  {
    "first_name": "Frank",
    "last_name": "Reynolds",
    "email": "wolfcola@wolfcola.com",
    "password": "frank123",
    "gender": "Male",
    "fitness_level": "Intermediate",
    "city": "Wekiwa",
    "state": "Florida",
    "age": "55",
    "availability": "Evening"
  },
  {
    "first_name": "Wayne",
    "last_name": "Wayons",
    "email": "wwayons@verizone.net",
    "password": "password",
    "gender": "Male",
    "fitness_level": "Beginner",
    "city": "Maitland",
    "state": "Florida",
    "age": "47",
    "availability": "Afternoon"
  },
  {
    "first_name": "Heather",
    "last_name": "Reynolds",
    "email": "heatherr@gmail.com",
    "password": "mynewpassword",
    "gender": "Female",
    "fitness_level": "Intermediate",
    "city": "Casselberry",
    "state": "Florida",
    "age": "31",
    "availability": "Evening"
  }
]
